anyconfig_json5_backend/__init__.py
anyconfig_json5_backend/json5_.py
anyconfig_json5_backend-0.2.0.dist-info/LICENSE.MIT
anyconfig_json5_backend-0.2.0.dist-info/METADATA
anyconfig_json5_backend-0.2.0.dist-info/WHEEL
anyconfig_json5_backend-0.2.0.dist-info/entry_points.txt
anyconfig_json5_backend-0.2.0.dist-info/top_level.txt
anyconfig_json5_backend-0.2.0.dist-info/RECORD
